repello_agent_wiz/__init__.py
repello_agent_wiz/cli.py
repello_agent_wiz/analyzers/__init__.py
repello_agent_wiz/analyzers/maestro.txt
repello_agent_wiz/analyzers/sys_prompt.txt
repello_agent_wiz/analyzers/threat_modelling.py
repello_agent_wiz/frameworks/__init__.py
repello_agent_wiz/frameworks/agent_chat/__init__.py
repello_agent_wiz/frameworks/agent_chat/mapper.py
repello_agent_wiz/frameworks/autogen/__init__.py
repello_agent_wiz/frameworks/autogen/mapper.py
repello_agent_wiz/frameworks/crewai/__init__.py
repello_agent_wiz/frameworks/crewai/mapper.py
repello_agent_wiz/frameworks/langgraph/__init__.py
repello_agent_wiz/frameworks/langgraph/mapper.py
repello_agent_wiz/frameworks/llama_index/__init__.py
repello_agent_wiz/frameworks/llama_index/mapper.py
repello_agent_wiz/frameworks/n8n/__init__.py
repello_agent_wiz/frameworks/n8n/mapper.py
repello_agent_wiz/frameworks/openai_agents/__init__.py
repello_agent_wiz/frameworks/openai_agents/mapper.py
repello_agent_wiz/frameworks/pydantic/__init__.py
repello_agent_wiz/frameworks/pydantic/mapper.py
repello_agent_wiz/frameworks/swarm/__init__.py
repello_agent_wiz/frameworks/swarm/mapper.py
repello_agent_wiz/templates/__init__.py
repello_agent_wiz/templates/index.html
repello_agent_wiz/templates/assets/Manrope-VariableFont_wght.ttf
repello_agent_wiz/templates/assets/Planner.svg
repello_agent_wiz/templates/assets/agent.svg
repello_agent_wiz/templates/assets/database.svg
repello_agent_wiz/templates/assets/end.svg
repello_agent_wiz/templates/assets/generic.svg
repello_agent_wiz/templates/assets/input.svg
repello_agent_wiz/templates/assets/mapper_bg.svg
repello_agent_wiz/templates/assets/memory.svg
repello_agent_wiz/templates/assets/output.svg
repello_agent_wiz/templates/assets/reflection.svg
repello_agent_wiz/templates/assets/search.svg
repello_agent_wiz/templates/assets/start.svg
repello_agent_wiz/templates/assets/tool.svg
repello_agent_wiz/visualizers/__init__.py
repello_agent_wiz/visualizers/visualizer.py
repello_agent_wiz-0.4.0.dist-info/licenses/LICENSE
repello_agent_wiz-0.4.0.dist-info/METADATA
repello_agent_wiz-0.4.0.dist-info/WHEEL
repello_agent_wiz-0.4.0.dist-info/entry_points.txt
repello_agent_wiz-0.4.0.dist-info/top_level.txt
repello_agent_wiz-0.4.0.dist-info/RECORD
