Metadata-Version: 2.4
Name: repello-agent-wiz
Version: 0.4.0
Summary: Generate agentic workflows visualizations & threat modelling reports for your agentic projects.
Author-email: Aryan Ranjan <aryan@repello.ai>, Aaditya Gupta <aadityagupta400@gmail.com>
License: Apache-2.0
Project-URL: Homepage, https://github.com/Repello-AI/agent-wiz/
Project-URL: Bug Tracker, https://github.com/Repello-AI/wiz/issues
Classifier: License :: OSI Approved :: Apache Software License
Classifier: Programming Language :: Python :: 3
Classifier: Operating System :: OS Independent
Classifier: Topic :: Software Development :: Libraries
Classifier: Topic :: Security
Requires-Python: >=3.10
License-File: LICENSE
Requires-Dist: openai
Dynamic: license-file
